sincpro_py_compiler/__init__.py
sincpro_py_compiler/cli.py
sincpro_py_compiler/decrypt_cli.py
sincpro_py_compiler/domain/__init__.py
sincpro_py_compiler/domain/compiler_service.py
sincpro_py_compiler/domain/security_service.py
sincpro_py_compiler/infrastructure/__init__.py
sincpro_py_compiler/infrastructure/compiler_service.py
sincpro_py_compiler/infrastructure/compression_service.py
sincpro_py_compiler/infrastructure/encryption_service.py
sincpro_py_compiler/infrastructure/file_manager.py
sincpro_py_compiler/infrastructure/python_compiler.py
sincpro_py_compiler/infrastructure/security_manager.py
sincpro_py_compiler/resources/__init__.py
sincpro_py_compiler/resources/exclude_patterns/basic.txt
sincpro_py_compiler/resources/exclude_patterns/django.txt
sincpro_py_compiler/resources/exclude_patterns/odoo.txt
sincpro_py_compiler/resources/resource_manager.py
sincpro_py_compiler-0.2.1.dist-info/LICENSE
sincpro_py_compiler-0.2.1.dist-info/METADATA
sincpro_py_compiler-0.2.1.dist-info/WHEEL
sincpro_py_compiler-0.2.1.dist-info/entry_points.txt
sincpro_py_compiler-0.2.1.dist-info/RECORD
