Metadata-Version: 2.3
Name: sincpro-py-compiler
Version: 0.2.1
Summary: Herramienta simple para compilar proyectos Python (.py → .pyc) y distribuir código compilado con protección por contraseña
License: MIT
Keywords: python,compiler,pyc,build,packaging,distribution,security,encryption,password-protection
Author: Sincpro SRL
Author-email: dev@sincpro.com
Requires-Python: >=3.10,<4.0
Classifier: Development Status :: 5 - Production/Stable
Classifier: Intended Audience :: Developers
Classifier: License :: OSI Approved :: MIT License
Classifier: Operating System :: OS Independent
Classifier: Programming Language :: Python :: 3
Classifier: Programming Language :: Python :: 3.10
Classifier: Programming Language :: Python :: 3.11
Classifier: Programming Language :: Python :: 3.12
Classifier: Programming Language :: Python :: 3.13
Classifier: Topic :: Software Development :: Build Tools
Classifier: Topic :: Software Development :: Compilers
Provides-Extra: encryption
Requires-Dist: cryptography (>=43.0.0,<44.0.0) ; extra == "encryption"
Project-URL: Documentation, https://github.com/Sincpro-SRL/sincpro_py_compiler/tree/main/docs
Project-URL: Homepage, https://github.com/Sincpro-SRL/sincpro_py_compiler
Project-URL: Repository, https://github.com/Sincpro-SRL/sincpro_py_compiler
